.gitignore
LICENSE
MANIFEST.in
README.md
setup.py
tests.py
notdb_viewer/__init__.py
notdb_viewer/__main__.py
notdb_viewer.egg-info/PKG-INFO
notdb_viewer.egg-info/SOURCES.txt
notdb_viewer.egg-info/dependency_links.txt
notdb_viewer.egg-info/entry_points.txt
notdb_viewer.egg-info/not-zip-safe
notdb_viewer.egg-info/requires.txt
notdb_viewer.egg-info/top_level.txt
notdb_viewer/app/__init__.py
notdb_viewer/app/templates/files.html
notdb_viewer/app/templates/viewer.html