Metadata-Version: 2.1
Name: notdb-viewer
Version: 1.3.0
Summary: Viewer for NotDB Databases
Home-page: https://github.com/nawafalqari/NotDB_Viewer/
Author: Nawaf Alqari
Author-email: nawafalqari13@gmail.com
License: MIT
Project-URL: Documentation, https://github.com/nawafalqari/NotDB_Viewer#readme
Project-URL: Bug Tracker, https://github.com/nawafalqari/NotDB_Viewer/issues
Project-URL: Source Code, https://github.com/nawafalqari/NotDB_Viewer/
Project-URL: Discord, https://discord.gg/cpvynqk4XT
Project-URL: Donate, https://paypal.me/NawafHAlqari
Keywords: notdb,db,database,notdatabsae,simple database
Platform: UNKNOWN
Classifier: Programming Language :: Python :: 3
Classifier: License :: OSI Approved :: MIT License
Classifier: Operating System :: OS Independent
Classifier: Topic :: Database
License-File: LICENSE
